tiktok_ads_mcp/__init__.py
tiktok_ads_mcp/__main__.py
tiktok_ads_mcp/client.py
tiktok_ads_mcp/config.py
tiktok_ads_mcp/main.py
tiktok_ads_mcp/server.py
tiktok_ads_mcp/tools/__init__.py
tiktok_ads_mcp/tools/get_ad_groups.py
tiktok_ads_mcp/tools/get_ads.py
tiktok_ads_mcp/tools/get_authorized_ad_accounts.py
tiktok_ads_mcp/tools/get_business_centers.py
tiktok_ads_mcp/tools/get_campaigns.py
tiktok_ads_mcp/tools/reports.py
tiktok_ads_mcp-0.1.2.dist-info/METADATA
tiktok_ads_mcp-0.1.2.dist-info/WHEEL
tiktok_ads_mcp-0.1.2.dist-info/entry_points.txt
tiktok_ads_mcp-0.1.2.dist-info/licenses/LICENSE
tiktok_ads_mcp-0.1.2.dist-info/RECORD
