Metadata-Version: 2.4
Name: tiktok-ads-mcp
Version: 0.1.2
Summary: Model Context Protocol (MCP) plugin for interacting with TikTok Ads API
Project-URL: Homepage, https://github.com/ysntony/tiktok-ads-mcp
Project-URL: Repository, https://github.com/ysntony/tiktok-ads-mcp
Project-URL: Documentation, https://github.com/ysntony/tiktok-ads-mcp#readme
Project-URL: Bug Tracker, https://github.com/ysntony/tiktok-ads-mcp/issues
Project-URL: Changelog, https://github.com/ysntony/tiktok-ads-mcp/blob/main/README.md#changelog
Author-email: Yu Shengnan <yushengnan0525@gmail.com>
License: MIT
License-File: LICENSE
Keywords: ads,advertising,api,marketing,mcp,model-context-protocol,tiktok
Classifier: Development Status :: 4 - Beta
Classifier: Intended Audience :: Developers
Classifier: License :: OSI Approved :: MIT License
Classifier: Operating System :: OS Independent
Classifier: Programming Language :: Python :: 3
Classifier: Topic :: Internet :: WWW/HTTP :: Dynamic Content
Classifier: Topic :: Software Development :: Libraries :: Python Modules
Requires-Python: >=3.8
Requires-Dist: mcp>=1.9.0
Requires-Dist: pandas>=2.2.0
Requires-Dist: python-dotenv>=1.0.0
Requires-Dist: requests>=2.32.3
Provides-Extra: dev
Requires-Dist: black>=23.0.0; extra == 'dev'
Requires-Dist: build>=1.0.0; extra == 'dev'
Requires-Dist: flake8>=6.0.0; extra == 'dev'
Requires-Dist: mypy>=1.0.0; extra == 'dev'
Requires-Dist: pytest-asyncio>=0.21.0; extra == 'dev'
Requires-Dist: pytest>=7.0.0; extra == 'dev'
Requires-Dist: twine>=4.0.0; extra == 'dev'
